robotica/__init__.py
robotica/__main__.py
robotica/cli.py
robotica/executor.py
robotica/schedule.py
robotica/types.py
robotica/plugins/__init__.py
robotica/plugins/inputs/__init__.py
robotica/plugins/inputs/http.py
robotica/plugins/inputs/mqtt.py
robotica/plugins/outputs/__init__.py
robotica/plugins/outputs/audio.py
robotica/plugins/outputs/lifx.py
robotica/plugins/outputs/mqtt.py
robotica-0.1.42.dist-info/DESCRIPTION.rst
robotica-0.1.42.dist-info/METADATA
robotica-0.1.42.dist-info/RECORD
robotica-0.1.42.dist-info/WHEEL
robotica-0.1.42.dist-info/entry_points.txt
robotica-0.1.42.dist-info/metadata.json
robotica-0.1.42.dist-info/top_level.txt
