Metadata-Version: 2.0
Name: robotica
Version: 0.1.42
Summary: Robotic maid to scare innocent children
Home-page: https://github.com/brianmay/robotica
Author: Brian May
Author-email: brian@linuxpenguins.xyz
License: GNU General Public License v3
Keywords: robotica
Platform: UNKNOWN
Classifier: Development Status :: 2 - Pre-Alpha
Classifier: Intended Audience :: Developers
Classifier: License :: OSI Approved :: GNU General Public License v3 (GPLv3)
Classifier: Natural Language :: English
Classifier: Programming Language :: Python :: 3.5
Classifier: Programming Language :: Python :: 3.6
Requires-Dist: aiohttp
Requires-Dist: Click (>=6.0)
Requires-Dist: APScheduler
Requires-Dist: click-log
Requires-Dist: hbmqtt
Requires-Dist: aiolifxc (>=0.5.2)
Requires-Dist: PyYAML
Requires-Dist: python-dateutil
